includecpp/CHANGELOG.md
includecpp/DOCUMENTATION.md
includecpp/__init__.py
includecpp/__init__.pyi
includecpp/__main__.py
includecpp/py.typed
includecpp/cli/__init__.py
includecpp/cli/commands.py
includecpp/cli/config_parser.py
includecpp/core/__init__.py
includecpp/core/ai_integration.py
includecpp/core/build_manager.py
includecpp/core/cpp_api.py
includecpp/core/cpp_api.pyi
includecpp/core/cpp_api_extensions.pyi
includecpp/core/cppy_converter.py
includecpp/core/cssl_bridge.py
includecpp/core/cssl_bridge.pyi
includecpp/core/error_catalog.py
includecpp/core/error_formatter.py
includecpp/core/exceptions.py
includecpp/core/homeserver.py
includecpp/core/path_discovery.py
includecpp/core/project_ui.py
includecpp/core/settings_ui.py
includecpp/core/cssl/CSSL_DOCUMENTATION.md
includecpp/core/cssl/CSSL_DOCUMENTATION_NEW.md
includecpp/core/cssl/__init__.py
includecpp/core/cssl/cssl_builtins.py
includecpp/core/cssl/cssl_builtins.pyi
includecpp/core/cssl/cssl_compiler.py
includecpp/core/cssl/cssl_events.py
includecpp/core/cssl/cssl_gui.py
includecpp/core/cssl/cssl_keyboard.py
includecpp/core/cssl/cssl_languages.py
includecpp/core/cssl/cssl_messagebox.py
includecpp/core/cssl/cssl_modules.py
includecpp/core/cssl/cssl_optimizer.py
includecpp/core/cssl/cssl_parser.py
includecpp/core/cssl/cssl_runtime.py
includecpp/core/cssl/cssl_syntax.py
includecpp/core/cssl/cssl_types.py
includecpp/core/cssl/cpp/cssl_core.cp
includecpp/core/cssl/cpp/cssl_lexer.hpp
includecpp/core/cssl/cpp/build/api.pyd
includecpp/core/cssl/cpp/build/api.pyi
includecpp/core/cssl/cpp/build/cssl_core.pyi
includecpp/core/cssl/cpp/build/libgcc_s_seh-1.dll
includecpp/core/cssl/cpp/build/libstdc++-6.dll
includecpp/core/cssl/cpp/build/libwinpthread-1.dll
includecpp/generator/__init__.py
includecpp/generator/parser.cpp
includecpp/generator/parser.h
includecpp/generator/type_resolver.cpp
includecpp/generator/type_resolver.h
includecpp/templates/cpp.proj.template
includecpp/vscode/__init__.py
includecpp-4.9.7.dist-info/licenses/LICENSE
includecpp-4.9.7.dist-info/METADATA
includecpp-4.9.7.dist-info/WHEEL
includecpp-4.9.7.dist-info/entry_points.txt
includecpp-4.9.7.dist-info/top_level.txt
includecpp-4.9.7.dist-info/RECORD
