Metadata-Version: 2.4
Name: IncludeCPP
Version: 4.9.7
Summary: Professional C++ Python bindings with type-generic templates, pystubs and native threading
Home-page: https://github.com/liliassg/IncludeCPP
Author: Lilias Hatterscheidt
Author-email: Lilias Hatterscheidt <hatterscheidt.lilias@gmail.com>
License: MIT
Project-URL: Repository, https://github.com/liliassg/IncludeCPP
Project-URL: Bug Tracker, https://github.com/liliassg/IncludeCPP/issues
Keywords: c++,python,bindings,pybind11,template,performance,threading
Classifier: Development Status :: 4 - Beta
Classifier: Intended Audience :: Developers
Classifier: Topic :: Software Development :: Libraries :: Python Modules
Classifier: Programming Language :: Python :: 3.9
Classifier: Programming Language :: Python :: 3.10
Classifier: Programming Language :: Python :: 3.11
Classifier: Programming Language :: Python :: 3.12
Classifier: Programming Language :: Python :: 3.13
Classifier: Programming Language :: C++
Classifier: License :: OSI Approved :: MIT License
Classifier: Operating System :: OS Independent
Requires-Python: >=3.8
License-File: LICENSE
Requires-Dist: pybind11>=2.11.0
Requires-Dist: click>=8.0.0
Requires-Dist: typing-extensions>=4.0.0
Requires-Dist: requests>=2.28.0
Requires-Dist: colorama>=0.4.0
Dynamic: author
Dynamic: home-page
Dynamic: license-file
Dynamic: requires-python
